[
  {
    "name": "Ariaria International Market",
    "description": "One of the largest markets in West Africa, ideal for shopping local textiles, footwear, and electronics.",
    "category": "Shopping & Culture",
    "location": "Aba",
    "image": "images/ariaria_international_market"
  },
  {
    "name": "National Museum of Colonial History",
    "description": "Explore Nigeria’s colonial past with rare artifacts, historical documents, and exhibitions.",
    "category": "History & Education",
    "location": "Aba",
    "image": "images/national-museum.jpg"
  },
  {
    "name": "Enyimba Stadium",
    "description": "Catch a match or tour the home of Enyimba FC, one of Nigeria’s most successful football clubs.",
    "category": "Sports & Entertainment",
    "location": "Aba",
    "image": "images/enyimba-stadium.jpg"
  },
  {
    "name": "Cenotaph Aba (Aba Memorial Park)",
    "description": "A peaceful monument commemorating war heroes, perfect for history lovers and reflection.",
    "category": "History & Memorial",
    "location": "Aba",
    "image": "images/aba-cenotaph.jpg"
  },
  {
    "name": "Ngwa Road Textile Market",
    "description": "Discover colorful African prints, fabrics, and tailoring craft from local designers.",
    "category": "Culture & Shopping",
    "location": "Aba",
    "image": "images/ngwa-market.jpg"
  },
  {
    "name": "Azumini Blue River",
    "description": "Located just outside Aba, this natural clear-blue river offers canoe rides, picnics, and swimming.",
    "category": "Nature & Recreation",
    "location": "Azumini (near Aba)",
    "image": "images/azumini-river.jpg"
  },
  {
    "name": "Shoprite Aba (Osisioma)",
    "description": "Modern shopping, food courts, and entertainment all in one accessible location.",
    "category": "Leisure & Shopping",
    "location": "Osisioma, Aba",
    "image": "images/shoprite-aba.jpg"
  },
  {
    "name": "Brass Monkey Restaurant & Lounge",
    "description": "Trendy spot for local dishes, drinks, and nightlife in a relaxed atmosphere.",
    "category": "Food & Nightlife",
    "location": "Aba",
    "image": "images/brass-monkey.jpg"
  },
  {
    "name": "TONIMAS Event Centre",
    "description": "Frequent host of local events, trade fairs, and cultural showcases — great for networking.",
    "category": "Events & Culture",
    "location": "Aba",
    "image": "images/tonimas-centre.jpg"
  },
  {
    "name": "Aba Sports Club",
    "description": "A family-friendly spot with tennis courts, a swimming pool, and recreational activities.",
    "category": "Leisure & Sports",
    "location": "Aba",
    "image": "images/aba-sports-club.jpg"
  }
]
